Plython/__init__.py
Plython/module.py
Plython-0.2.dist-info/LICENSE
Plython-0.2.dist-info/METADATA
Plython-0.2.dist-info/WHEEL
Plython-0.2.dist-info/top_level.txt
Plython-0.2.dist-info/RECORD
